NOrbit.py
__init__.py
NOrbit-1.0.2.dist-info/LICENSE
NOrbit-1.0.2.dist-info/METADATA
NOrbit-1.0.2.dist-info/WHEEL
NOrbit-1.0.2.dist-info/top_level.txt
NOrbit-1.0.2.dist-info/RECORD
