Metadata-Version: 2.1
Name: NOrbit
Version: 1.0.2
Summary: A package for N-body integration using the Runge-Kutta 4th Order Method
Author-email: Lukas Orion <a11919257@unet.univie.ac.at>, Jim Buisman <a01625563@unet.univie.ac.at>
License: 
Project-URL: Homepage, https://github.com/Lukas-Orion/NOrbit
Project-URL: Repository, https://github.com/Lukas-Orion/NOrbit
Project-URL: Bug Tracker, https://github.com/Lukas-Orion/NOrbit/issues
Requires-Python: >=3.8
License-File: LICENSE
Requires-Dist: numpy >=1.23
Requires-Dist: pydantic
Provides-Extra: plot
Requires-Dist: matplotlib ; extra == 'plot'
